{
   "runs" : [
      {
         "OS" : "linux",
         "abstract" : "Comprehensive GitHub Actions workflow generator, analyzer, and optimizer",
         "dir" : "/home/runner/work/App-GHGen/App-GHGen",
         "finish" : 1768925439.60858,
         "name" : "App-GHGen",
         "perl" : "5.40.3",
         "run" : "-e",
         "start" : 1768925439.60823,
         "version" : "0.01"
      },
      {
         "OS" : "linux",
         "abstract" : "Comprehensive GitHub Actions workflow generator, analyzer, and optimizer",
         "dir" : "/home/runner/work/App-GHGen/App-GHGen",
         "finish" : 1768925439.78126,
         "name" : "App-GHGen",
         "perl" : "5.40.3",
         "run" : "-e",
         "start" : 1768925439.78104,
         "version" : "0.01"
      },
      {
         "OS" : "linux",
         "abstract" : "Comprehensive GitHub Actions workflow generator, analyzer, and optimizer",
         "dir" : "/home/runner/work/App-GHGen/App-GHGen",
         "finish" : 1768925439.94779,
         "name" : "App-GHGen",
         "perl" : "5.40.3",
         "run" : "-e",
         "start" : 1768925439.94748,
         "version" : "0.01"
      },
      {
         "OS" : "linux",
         "abstract" : "Comprehensive GitHub Actions workflow generator, analyzer, and optimizer",
         "dir" : "/home/runner/work/App-GHGen/App-GHGen",
         "finish" : 1768925440.11326,
         "name" : "App-GHGen",
         "perl" : "5.40.3",
         "run" : "-e",
         "start" : 1768925440.11293,
         "version" : "0.01"
      },
      {
         "OS" : "linux",
         "abstract" : "Comprehensive GitHub Actions workflow generator, analyzer, and optimizer",
         "dir" : "/home/runner/work/App-GHGen/App-GHGen",
         "finish" : 1768925440.28358,
         "name" : "App-GHGen",
         "perl" : "5.40.3",
         "run" : "-e",
         "start" : 1768925440.28327,
         "version" : "0.01"
      },
      {
         "OS" : "linux",
         "abstract" : "Comprehensive GitHub Actions workflow generator, analyzer, and optimizer",
         "dir" : "/home/runner/work/App-GHGen/App-GHGen",
         "finish" : 1768925440.45311,
         "name" : "App-GHGen",
         "perl" : "5.40.3",
         "run" : "-e",
         "start" : 1768925440.45285,
         "version" : "0.01"
      },
      {
         "OS" : "linux",
         "abstract" : "Comprehensive GitHub Actions workflow generator, analyzer, and optimizer",
         "dir" : "/home/runner/work/App-GHGen/App-GHGen",
         "finish" : 1768925440.62518,
         "name" : "App-GHGen",
         "perl" : "5.40.3",
         "run" : "-e",
         "start" : 1768925440.62488,
         "version" : "0.01"
      },
      {
         "OS" : "linux",
         "abstract" : "Comprehensive GitHub Actions workflow generator, analyzer, and optimizer",
         "dir" : "/home/runner/work/App-GHGen/App-GHGen",
         "finish" : 1768925440.80202,
         "name" : "App-GHGen",
         "perl" : "5.40.3",
         "run" : "-e",
         "start" : 1768925440.80173,
         "version" : "0.01"
      },
      {
         "OS" : "linux",
         "abstract" : "Comprehensive GitHub Actions workflow generator, analyzer, and optimizer",
         "dir" : "/home/runner/work/App-GHGen/App-GHGen",
         "finish" : 1768925441.00388,
         "name" : "App-GHGen",
         "perl" : "5.40.3",
         "run" : "-e",
         "start" : 1768925440.98314,
         "version" : "0.01"
      },
      {
         "OS" : "linux",
         "abstract" : "Comprehensive GitHub Actions workflow generator, analyzer, and optimizer",
         "dir" : "/home/runner/work/App-GHGen/App-GHGen",
         "finish" : 1768925441.23773,
         "name" : "App-GHGen",
         "perl" : "5.40.3",
         "run" : "-e",
         "start" : 1768925441.23711,
         "version" : "0.01"
      },
      {
         "OS" : "linux",
         "abstract" : "Comprehensive GitHub Actions workflow generator, analyzer, and optimizer",
         "dir" : "/home/runner/work/App-GHGen/App-GHGen",
         "finish" : 1768925443.31801,
         "name" : "App-GHGen",
         "perl" : "5.40.3",
         "run" : "-e",
         "start" : 1768925441.44439,
         "version" : "0.01"
      },
      {
         "OS" : "linux",
         "abstract" : "Comprehensive GitHub Actions workflow generator, analyzer, and optimizer",
         "dir" : "/home/runner/work/App-GHGen/App-GHGen",
         "finish" : 1768925441.61385,
         "name" : "App-GHGen",
         "perl" : "5.40.3",
         "run" : "-e",
         "start" : 1768925441.61372,
         "version" : "0.01"
      },
      {
         "OS" : "linux",
         "abstract" : "Comprehensive GitHub Actions workflow generator, analyzer, and optimizer",
         "dir" : "/home/runner/work/App-GHGen/App-GHGen",
         "finish" : 1768925441.87584,
         "name" : "App-GHGen",
         "perl" : "5.40.3",
         "run" : "t/30-basics.t",
         "start" : 1768925441.8602,
         "version" : "0.01"
      },
      {
         "OS" : "linux",
         "abstract" : "Comprehensive GitHub Actions workflow generator, analyzer, and optimizer",
         "dir" : "/home/runner/work/App-GHGen/App-GHGen",
         "finish" : 1768925442.23653,
         "name" : "App-GHGen",
         "perl" : "5.40.3",
         "run" : "t/detector.t",
         "start" : 1768925442.2177,
         "version" : "0.01"
      },
      {
         "OS" : "linux",
         "abstract" : "Comprehensive GitHub Actions workflow generator, analyzer, and optimizer",
         "dir" : "/home/runner/work/App-GHGen/App-GHGen",
         "finish" : 1768925442.5432,
         "name" : "App-GHGen",
         "perl" : "5.40.3",
         "run" : "t/eof.t",
         "start" : 1768925442.54291,
         "version" : "0.01"
      },
      {
         "OS" : "linux",
         "abstract" : "Comprehensive GitHub Actions workflow generator, analyzer, and optimizer",
         "dir" : "/home/runner/work/App-GHGen/App-GHGen",
         "finish" : 1768925442.78972,
         "name" : "App-GHGen",
         "perl" : "5.40.3",
         "run" : "t/eol.t",
         "start" : 1768925442.78946,
         "version" : "0.01"
      },
      {
         "OS" : "linux",
         "abstract" : "Comprehensive GitHub Actions workflow generator, analyzer, and optimizer",
         "dir" : "/home/runner/work/App-GHGen/App-GHGen",
         "finish" : 1768925443.03113,
         "name" : "App-GHGen",
         "perl" : "5.40.3",
         "run" : "t/pod-cm.t",
         "start" : 1768925443.03085,
         "version" : "0.01"
      },
      {
         "OS" : "linux",
         "abstract" : "Comprehensive GitHub Actions workflow generator, analyzer, and optimizer",
         "dir" : "/home/runner/work/App-GHGen/App-GHGen",
         "finish" : 1768925443.27449,
         "name" : "App-GHGen",
         "perl" : "5.40.3",
         "run" : "t/pod-coverage.t",
         "start" : 1768925443.27423,
         "version" : "0.01"
      }
   ],
   "summary" : {
      "Total" : {
         "branch" : {
            "covered" : 135,
            "error" : 119,
            "percentage" : 53.1496062992126,
            "total" : 254,
            "uncoverable" : 0
         },
         "condition" : {
            "covered" : 31,
            "error" : 52,
            "percentage" : 37.3493975903614,
            "total" : 83,
            "uncoverable" : 0
         },
         "statement" : {
            "covered" : 455,
            "error" : 75,
            "percentage" : 85.8490566037736,
            "total" : 530
         },
         "subroutine" : {
            "covered" : 51,
            "error" : 14,
            "percentage" : 78.4615384615385,
            "total" : 65
         },
         "total" : {
            "covered" : 672,
            "error" : 260,
            "percentage" : 72.1030042918455,
            "total" : 932,
            "uncoverable" : 0
         }
      },
      "blib/lib/App/GHGen.pm" : {
         "statement" : {
            "covered" : 8,
            "percentage" : 100,
            "total" : 8
         },
         "subroutine" : {
            "covered" : 3,
            "percentage" : 100,
            "total" : 3
         },
         "total" : {
            "covered" : 11,
            "percentage" : 100,
            "total" : 11
         }
      },
      "blib/lib/App/GHGen/Analyzer.pm" : {
         "branch" : {
            "covered" : 31,
            "error" : 41,
            "percentage" : 43.0555555555556,
            "total" : 72,
            "uncoverable" : 0
         },
         "condition" : {
            "covered" : 8,
            "error" : 20,
            "percentage" : 28.5714285714286,
            "total" : 28,
            "uncoverable" : 0
         },
         "statement" : {
            "covered" : 104,
            "error" : 32,
            "percentage" : 76.4705882352941,
            "total" : 136
         },
         "subroutine" : {
            "covered" : 14,
            "error" : 3,
            "percentage" : 82.3529411764706,
            "total" : 17
         },
         "total" : {
            "covered" : 157,
            "error" : 96,
            "percentage" : 62.0553359683794,
            "total" : 253,
            "uncoverable" : 0
         }
      },
      "blib/lib/App/GHGen/Detector.pm" : {
         "branch" : {
            "covered" : 95,
            "error" : 69,
            "percentage" : 57.9268292682927,
            "total" : 164,
            "uncoverable" : 0
         },
         "condition" : {
            "covered" : 11,
            "error" : 19,
            "percentage" : 36.6666666666667,
            "total" : 30,
            "uncoverable" : 0
         },
         "statement" : {
            "covered" : 154,
            "error" : 2,
            "percentage" : 98.7179487179487,
            "total" : 156
         },
         "subroutine" : {
            "covered" : 17,
            "percentage" : 100,
            "total" : 17
         },
         "total" : {
            "covered" : 277,
            "error" : 90,
            "percentage" : 75.4768392370572,
            "total" : 367,
            "uncoverable" : 0
         }
      },
      "blib/lib/App/GHGen/Generator.pm" : {
         "branch" : {
            "covered" : 2,
            "error" : 0,
            "percentage" : 100,
            "total" : 2,
            "uncoverable" : 0
         },
         "condition" : {
            "covered" : 1,
            "error" : 1,
            "percentage" : 50,
            "total" : 2,
            "uncoverable" : 0
         },
         "statement" : {
            "covered" : 28,
            "error" : 35,
            "percentage" : 44.4444444444444,
            "total" : 63
         },
         "subroutine" : {
            "covered" : 8,
            "error" : 11,
            "percentage" : 42.1052631578947,
            "total" : 19
         },
         "total" : {
            "covered" : 39,
            "error" : 47,
            "percentage" : 45.3488372093023,
            "total" : 86,
            "uncoverable" : 0
         }
      },
      "blib/lib/App/GHGen/PerlCustomizer.pm" : {
         "branch" : {
            "covered" : 7,
            "error" : 9,
            "percentage" : 43.75,
            "total" : 16,
            "uncoverable" : 0
         },
         "condition" : {
            "covered" : 11,
            "error" : 12,
            "percentage" : 47.8260869565217,
            "total" : 23,
            "uncoverable" : 0
         },
         "statement" : {
            "covered" : 161,
            "error" : 6,
            "percentage" : 96.4071856287425,
            "total" : 167
         },
         "subroutine" : {
            "covered" : 9,
            "percentage" : 100,
            "total" : 9
         },
         "total" : {
            "covered" : 188,
            "error" : 27,
            "percentage" : 87.4418604651163,
            "total" : 215,
            "uncoverable" : 0
         }
      }
   }
}
